{"id":"100","title":"加密市场现在平均跌了30%price in的是周一开盘标普500跌5%这种变态跌幅但是如果周一标普500并没有跌想象中那么多，那么情绪就会快速修复","type":"text","datetime":"2025-10-11T21:49:35+00:00","tags":[],"text":"加密市场现在平均跌了30%price in的是周一开盘标普500跌5%这种变态跌幅但是如果周一标普500并没有跌想象中那么多，那么情绪就会快速修复。","content":"加密市场现在平均跌了30%<br>price in的是周一开盘标普500跌5%这种变态跌幅<br><br>但是如果周一标普500并没有跌想象中那么多，那么情绪就会快速修复。","reactions":[{"emoji":"👍","count":"221","isPaid":false},{"emoji":"🤔","count":"28","isPaid":false},{"emoji":"❤️","count":"21","isPaid":false},{"emoji":"😈","count":"7","isPaid":false},{"emoji":"🤩","count":"4","isPaid":false},{"emoji":"🏆","count":"2","isPaid":false},{"emoji":"👏","count":"1","isPaid":false}],"nextPostId":"101","prevPostId":"99"}