{"id":"356","title":"4400合约tp了一点","type":"text","datetime":"2025-08-12T13:05:44+00:00","tags":[],"text":"4400合约tp了一点","content":"<a class=\"tgme_widget_message_reply user-color-default\" href=\"/posts/354\" \"=\"\"><blockquote><small>\n<div class=\"tgme_widget_message_author accent_color\">\n  <span class=\"tgme_widget_message_author_name\" dir=\"auto\">Fiona’s daily news</span>\n</div>\n<div class=\"tgme_widget_message_text js-message_reply_text\" dir=\"auto\">买eth啦</div>\n</small></blockquote></a>4400合约tp了一点","reactions":[],"nextPostId":"357","prevPostId":"355"}