{"id":"419","title":"大阳线 终于等到你","type":"text","datetime":"2025-10-01T09:18:45+00:00","tags":[],"text":"大阳线 终于等到你","content":"<a class=\"tgme_widget_message_reply user-color-default\" href=\"/posts/413\" \"=\"\"><blockquote><small>\n<div class=\"tgme_widget_message_author accent_color\">\n  <span class=\"tgme_widget_message_author_name\" dir=\"auto\">Fiona’s daily news</span>\n</div>\n<div class=\"tgme_widget_message_text js-message_reply_text\" dir=\"auto\">早安，目前所有的抄底单，除了doge都盈利了。不过周一才刚开始也不想太早乐观。关注本周非农 失业率。</div>\n</small></blockquote></a>大阳线 终于等到你","reactions":[{"emoji":"❤️","count":"18","isPaid":false},{"emoji":"👏","count":"5","isPaid":false},{"emoji":"😁","count":"1","isPaid":false}],"nextPostId":"420","prevPostId":"418"}