{"id":"468","title":"抄底买的 $BTC 已卖","type":"text","datetime":"2025-12-30T01:29:11+00:00","tags":[],"text":"抄底买的 $BTC 已卖。上次上涨不卖过于后悔，这次一定抓住机会。等2026年再交易了～","content":"<a class=\"tgme_widget_message_reply user-color-default\" href=\"/posts/464\" \"=\"\"><blockquote><small>\n<div class=\"tgme_widget_message_author accent_color\">\n  <span class=\"tgme_widget_message_author_name\" dir=\"auto\">Fiona’s daily news</span>\n</div>\n<div class=\"tgme_widget_message_text js-message_reply_text\" dir=\"auto\">马上周一啦！复盘一下过去一周的操作： 抄底了 $BTC  $GOOG  $BMNR  周五开盘买了 $NBIS $AVGO，卖了 $PLTR Alts短期内不会买了，准备用BMNR来代替我的山寨持仓（更高波动率）  相信AI叙事没有结束，且Google会占据优势地位，同样也看好阿里巴巴。  接下来关注PCE（这是美联储真正关注的通胀指标），初请失业金数据，非农就业数据。</div>\n</small></blockquote></a>抄底买的 $BTC 已卖。上次上涨不卖过于后悔，这次一定抓住机会。等2026年再交易了～","reactions":[{"emoji":"👍","count":"18","isPaid":false},{"emoji":"❤️","count":"3","isPaid":false},{"emoji":"😱","count":"1","isPaid":false}],"nextPostId":"469","prevPostId":"467"}